ShynaWeather/GetShynaWeather.py
ShynaWeather/UpdateWeather.py
ShynaWeather/__init__.py
ShynaWeather-0.0.5.dist-info/LICENSE
ShynaWeather-0.0.5.dist-info/METADATA
ShynaWeather-0.0.5.dist-info/WHEEL
ShynaWeather-0.0.5.dist-info/top_level.txt
ShynaWeather-0.0.5.dist-info/RECORD
