Metadata-Version: 2.1
Name: ShynaWeather
Version: 0.0.5
Summary: This package will take care of maintaining the Weather details as per my last location.
Author: Shivam Sharma
Author-email: shivamsharma1913@gmail.com
License-File: LICENSE
Requires-Dist: ShynaDatabase
Requires-Dist: ShynaTime
Requires-Dist: requests
Requires-Dist: setuptools
Requires-Dist: wheel
